{
    "asset": {
        "format": "jpg",
        "id": "6af29434ed27643ac46fca85d4ae35d0",
        "name": "5e95a24576c5e.jpg",
        "path": "file:C:/repositories/NotsCaptchaDataset/images/images/5e95a24576c5e.jpg",
        "size": {
            "width": 800,
            "height": 200
        },
        "state": 2,
        "type": 1,
        "predicted": true
    },
    "regions": [
        {
            "id": "VITdfGVrl",
            "type": "RECTANGLE",
            "tags": [
                "S"
            ],
            "boundingBox": {
                "height": 77.13498622589532,
                "width": 66.71261199172984,
                "left": 338.5251550654721,
                "top": 60.81267217630854
            },
            "points": [
                {
                    "x": 338.5251550654721,
                    "y": 60.81267217630854
                },
                {
                    "x": 405.23776705720195,
                    "y": 60.81267217630854
                },
                {
                    "x": 405.23776705720195,
                    "y": 137.94765840220387
                },
                {
                    "x": 338.5251550654721,
                    "y": 137.94765840220387
                }
            ]
        },
        {
            "id": "67AK7zRbf",
            "type": "RECTANGLE",
            "tags": [
                "A"
            ],
            "boundingBox": {
                "height": 74.3801652892562,
                "width": 79.9448656099242,
                "left": 410.75120606478293,
                "top": 61.36363636363637
            },
            "points": [
                {
                    "x": 410.75120606478293,
                    "y": 61.36363636363637
                },
                {
                    "x": 490.6960716747071,
                    "y": 61.36363636363637
                },
                {
                    "x": 490.6960716747071,
                    "y": 135.74380165289256
                },
                {
                    "x": 410.75120606478293,
                    "y": 135.74380165289256
                }
            ]
        },
        {
            "id": "cOlQteVTr",
            "type": "RECTANGLE",
            "tags": [
                "T"
            ],
            "boundingBox": {
                "height": 80.44077134986226,
                "width": 53.480358373535495,
                "left": 495.1068228807719,
                "top": 53.09917355371901
            },
            "points": [
                {
                    "x": 495.1068228807719,
                    "y": 53.09917355371901
                },
                {
                    "x": 548.5871812543074,
                    "y": 53.09917355371901
                },
                {
                    "x": 548.5871812543074,
                    "y": 133.53994490358127
                },
                {
                    "x": 495.1068228807719,
                    "y": 133.53994490358127
                }
            ]
        },
        {
            "id": "b2N2mW9Vw",
            "type": "RECTANGLE",
            "tags": [
                "I"
            ],
            "boundingBox": {
                "height": 89.25619834710744,
                "width": 30.875258442453482,
                "left": 549.6898690558236,
                "top": 45.9366391184573
            },
            "points": [
                {
                    "x": 549.6898690558236,
                    "y": 45.9366391184573
                },
                {
                    "x": 580.5651274982771,
                    "y": 45.9366391184573
                },
                {
                    "x": 580.5651274982771,
                    "y": 135.19283746556474
                },
                {
                    "x": 549.6898690558236,
                    "y": 135.19283746556474
                }
            ]
        },
        {
            "id": "rR8ezma4K",
            "type": "RECTANGLE",
            "tags": [
                "N"
            ],
            "boundingBox": {
                "height": 72.72727272727273,
                "width": 77.7394900068918,
                "left": 582.2191592005514,
                "top": 64.11845730027548
            },
            "points": [
                {
                    "x": 582.2191592005514,
                    "y": 64.11845730027548
                },
                {
                    "x": 659.9586492074432,
                    "y": 64.11845730027548
                },
                {
                    "x": 659.9586492074432,
                    "y": 136.8457300275482
                },
                {
                    "x": 582.2191592005514,
                    "y": 136.8457300275482
                }
            ]
        },
        {
            "id": "9nOgTfP6b",
            "type": "RECTANGLE",
            "tags": [
                "Y"
            ],
            "boundingBox": {
                "height": 92.56198347107438,
                "width": 67.26395589248794,
                "left": 664.369400413508,
                "top": 60.26170798898072
            },
            "points": [
                {
                    "x": 664.369400413508,
                    "y": 60.26170798898072
                },
                {
                    "x": 731.6333563059959,
                    "y": 60.26170798898072
                },
                {
                    "x": 731.6333563059959,
                    "y": 152.8236914600551
                },
                {
                    "x": 664.369400413508,
                    "y": 152.8236914600551
                }
            ]
        }
    ],
    "version": "2.2.0"
}