{
    "asset": {
        "format": "jpg",
        "id": "7c7332ed0b9a91cfd02cf961293de5f6",
        "name": "5e95a8560163a.jpg",
        "path": "file:C:/source/NotsCaptchaDataset/images/images/5e95a8560163a.jpg",
        "size": {
            "width": 800,
            "height": 200
        },
        "state": 2,
        "type": 1,
        "predicted": true
    },
    "regions": [
        {
            "id": "v1kg6Rgku",
            "type": "RECTANGLE",
            "tags": [
                "E"
            ],
            "boundingBox": {
                "height": 64.46280991735537,
                "width": 72.22605099931083,
                "left": 278.4286698828395,
                "top": 70.73002754820936
            },
            "points": [
                {
                    "x": 278.4286698828395,
                    "y": 70.73002754820936
                },
                {
                    "x": 350.6547208821503,
                    "y": 70.73002754820936
                },
                {
                    "x": 350.6547208821503,
                    "y": 135.19283746556474
                },
                {
                    "x": 278.4286698828395,
                    "y": 135.19283746556474
                }
            ]
        },
        {
            "id": "0GwSgv880",
            "type": "RECTANGLE",
            "tags": [
                "A"
            ],
            "boundingBox": {
                "height": 78.23691460055096,
                "width": 86.56099241902137,
                "left": 355.0654720882151,
                "top": 63.01652892561984
            },
            "points": [
                {
                    "x": 355.0654720882151,
                    "y": 63.01652892561984
                },
                {
                    "x": 441.62646450723645,
                    "y": 63.01652892561984
                },
                {
                    "x": 441.62646450723645,
                    "y": 141.2534435261708
                },
                {
                    "x": 355.0654720882151,
                    "y": 141.2534435261708
                }
            ]
        },
        {
            "id": "uabEVDKXJ",
            "type": "RECTANGLE",
            "tags": [
                "S"
            ],
            "boundingBox": {
                "height": 79.33884297520662,
                "width": 69.46933149552034,
                "left": 446.03721571330124,
                "top": 61.36363636363637
            },
            "points": [
                {
                    "x": 446.03721571330124,
                    "y": 61.36363636363637
                },
                {
                    "x": 515.5065472088215,
                    "y": 61.36363636363637
                },
                {
                    "x": 515.5065472088215,
                    "y": 140.70247933884298
                },
                {
                    "x": 446.03721571330124,
                    "y": 140.70247933884298
                }
            ]
        },
        {
            "id": "O6M6zPM6a",
            "type": "RECTANGLE",
            "tags": [
                "I"
            ],
            "boundingBox": {
                "height": 90.35812672176309,
                "width": 27.567195037904895,
                "left": 516.0578911095796,
                "top": 46.48760330578513
            },
            "points": [
                {
                    "x": 516.0578911095796,
                    "y": 46.48760330578513
                },
                {
                    "x": 543.6250861474846,
                    "y": 46.48760330578513
                },
                {
                    "x": 543.6250861474846,
                    "y": 136.8457300275482
                },
                {
                    "x": 516.0578911095796,
                    "y": 136.8457300275482
                }
            ]
        },
        {
            "id": "8-osc52CY",
            "type": "RECTANGLE",
            "tags": [
                "E"
            ],
            "boundingBox": {
                "height": 71.07438016528926,
                "width": 77.7394900068918,
                "left": 545.830461750517,
                "top": 64.11845730027548
            },
            "points": [
                {
                    "x": 545.830461750517,
                    "y": 64.11845730027548
                },
                {
                    "x": 623.5699517574087,
                    "y": 64.11845730027548
                },
                {
                    "x": 623.5699517574087,
                    "y": 135.19283746556474
                },
                {
                    "x": 545.830461750517,
                    "y": 135.19283746556474
                }
            ]
        },
        {
            "id": "1Qr-ibkX0",
            "type": "RECTANGLE",
            "tags": [
                "R"
            ],
            "boundingBox": {
                "height": 71.07438016528926,
                "width": 54.03170227429359,
                "left": 628.5320468642316,
                "top": 64.6694214876033
            },
            "points": [
                {
                    "x": 628.5320468642316,
                    "y": 64.6694214876033
                },
                {
                    "x": 682.5637491385252,
                    "y": 64.6694214876033
                },
                {
                    "x": 682.5637491385252,
                    "y": 135.74380165289256
                },
                {
                    "x": 628.5320468642316,
                    "y": 135.74380165289256
                }
            ]
        }
    ],
    "version": "2.2.0"
}